[
  {
    "label": "Name",
    "name": "name",
    "type": "text",
    "required": true
  },
  {
    "label": "Shell",
    "name": "shell",
    "type": "text",
    "disabled": true
  },
  {
    "label": "Working Directory",
    "name": "workdir",
    "type": "text"
  },
  {
    "label": "Environment Variable",
    "name": "env_variables",
    "type": "table",
    "headers": [
      {
        "name": "key",
        "unique": true
      },
      {
        "name": "value"
      }
    ],
    "transform": "field"
  }
]